odoo10_addon_stock_account_operating_unit-10.0.1.0.1-nspkg.pth
odoo/addons/stock_account_operating_unit/README.rst
odoo/addons/stock_account_operating_unit/__init__.py
odoo/addons/stock_account_operating_unit/__manifest__.py
odoo/addons/stock_account_operating_unit/model/__init__.py
odoo/addons/stock_account_operating_unit/model/stock_move.py
odoo/addons/stock_account_operating_unit/model/stock_quant.py
odoo/addons/stock_account_operating_unit/static/description/icon.png
odoo/addons/stock_account_operating_unit/tests/__init__.py
odoo/addons/stock_account_operating_unit/tests/test_stock_account_operating_unit.py
odoo10_addon_stock_account_operating_unit-10.0.1.0.1.dist-info/METADATA
odoo10_addon_stock_account_operating_unit-10.0.1.0.1.dist-info/WHEEL
odoo10_addon_stock_account_operating_unit-10.0.1.0.1.dist-info/namespace_packages.txt
odoo10_addon_stock_account_operating_unit-10.0.1.0.1.dist-info/top_level.txt
odoo10_addon_stock_account_operating_unit-10.0.1.0.1.dist-info/RECORD
